veho/__init__.py
veho/columns/__init__.py
veho/columns/enumerate/__init__.py
veho/columns/enumerate/mapper/__init__.py
veho/columns/getter/__init__.py
veho/columns/mapper/__init__.py
veho/columns/updater/__init__.py
veho/dict/__init__.py
veho/dict/select/__init__.py
veho/entries/__init__.py
veho/entries/enumerate/__init__.py
veho/entries/enumerate/mapper/__init__.py
veho/entries/enumerate/mapper/mapper_entries.py
veho/entries/enumerate/mapper/mapper_keys.py
veho/entries/enumerate/mapper/mapper_values.py
veho/entries/enumerate/margin/__init__.py
veho/entries/enumerate/zipper/__init__.py
veho/entries/enumerate/zipper/mutazip.py
veho/entries/enumerate/zipper/series_zipper.py
veho/entries/enumerate/zipper/zipper.py
veho/entries/init/__init__.py
veho/entries/mapper/__init__.py
veho/entries/mapper/mapper_entries.py
veho/entries/mapper/mapper_keys.py
veho/entries/mapper/mapper_values.py
veho/entries/margin/__init__.py
veho/entries/unwind/__init__.py
veho/entries/zipper/__init__.py
veho/entries/zipper/mutazip.py
veho/entries/zipper/series_zipper.py
veho/entries/zipper/zipper.py
veho/enum/__init__.py
veho/enum/matrix_directions/__init__.py
veho/json/__init__.py
veho/json/init/__init__.py
veho/matrix/__init__.py
veho/matrix/enumerate/__init__.py
veho/matrix/enumerate/mapper/__init__.py
veho/matrix/enumerate/mapper/iterate.py
veho/matrix/enumerate/mapper/mapper.py
veho/matrix/enumerate/mapper/mutate.py
veho/matrix/enumerate/margin/__init__.py
veho/matrix/enumerate/zipper/__init__.py
veho/matrix/enumerate/zipper/mutazip.py
veho/matrix/enumerate/zipper/series_zipper.py
veho/matrix/enumerate/zipper/zipper.py
veho/matrix/init/__init__.py
veho/matrix/mapper/__init__.py
veho/matrix/mapper/iterate.py
veho/matrix/mapper/mapper.py
veho/matrix/mapper/mutate.py
veho/matrix/mapper/shallow.py
veho/matrix/margin/__init__.py
veho/matrix/select/__init__.py
veho/matrix/select/col.py
veho/matrix/select/row.py
veho/matrix/updater/__init__.py
veho/matrix/utils/__init__.py
veho-0.0.10.dist-info/WHEEL
veho-0.0.10.dist-info/METADATA
veho-0.0.10.dist-info/RECORD
