Metadata-Version: 2.1
Name: veho
Version: 0.0.10
Summary: easy enumerate
Home-page: https://github.com/pydget/veho
License: MIT
Keywords: list,array,vector,matrix,1d-list,2d-list,map,mapper,mutate,zipper,enumerate,iterate,entry,entries,key-value,key-value pairs,dict,object,json
Author: Hoyeung Wong
Author-email: hoyeungw@outlook.com
Requires-Python: >=3.8,<4.0
Classifier: License :: OSI Approved :: MIT License
Classifier: Programming Language :: Python :: 3
Classifier: Programming Language :: Python :: 3.8
Classifier: Programming Language :: Python :: 3.9
Project-URL: Repository, https://github.com/pydget/veho
